skx.cpython-313-darwin.so
skx-0.0.22.dist-info/RECORD
skx-0.0.22.dist-info/WHEEL
skx-0.0.22.dist-info/top_level.txt
skx-0.0.22.dist-info/METADATA
