Metadata-Version: 2.4
Name: skx
Version: 0.0.22
Summary: scikit-learn compatible extensions.
Author-email: skx <hi@sk-x.org>
License-Expression: GPL-3.0-or-later
Project-URL: homepage, https://pypi.org/project/skx
Project-URL: documentation, https://docs.sk-x.org
Keywords: scikit-learn,augmentation,resampling,smote,ensemble,voting,mixture-of-experts,mlp,neural-network,multi-output
Classifier: Programming Language :: Python :: 3
Classifier: Programming Language :: Python :: 3.12
Classifier: Programming Language :: Python :: 3.13
Classifier: Topic :: Scientific/Engineering :: Artificial Intelligence
Classifier: Operating System :: MacOS
Classifier: Operating System :: MacOS :: MacOS X
Classifier: Operating System :: POSIX :: Linux
Requires-Python: >=3.12
Requires-Dist: pandas<3.0,>=2.0
Requires-Dist: numpy<3.0,>=2.0
Requires-Dist: scikit-learn~=1.7.0
Requires-Dist: scipy<2.0,>=1.13
